README.md
setup.cfg
setup.py
GreyT_Signer.egg-info/PKG-INFO
GreyT_Signer.egg-info/SOURCES.txt
GreyT_Signer.egg-info/dependency_links.txt
GreyT_Signer.egg-info/entry_points.txt
GreyT_Signer.egg-info/not-zip-safe
GreyT_Signer.egg-info/requires.txt
GreyT_Signer.egg-info/top_level.txt
greyt_signer/__init__.py
greyt_signer/constant.py
greyt_signer/utils.py